docparser/__init__.py
docparser/constants.py
docparser/document.py
docparser/enums.py
docparser/exceptions.py
docparser/parser.py
docparser/reader.py
docparser/utils.py
docparser/xml_parser.py
python_docparser-1.1.0.dist-info/LICENCE.txt
python_docparser-1.1.0.dist-info/METADATA
python_docparser-1.1.0.dist-info/WHEEL
python_docparser-1.1.0.dist-info/top_level.txt
python_docparser-1.1.0.dist-info/RECORD
