Metadata-Version: 2.1
Name: python-docparser
Version: 1.1.0
Summary: Extract text from your docx document.
Home-page: https://github.com/has-abi/docparser
Author: Hassane Abida
Author-email: abidahass.uca@gmail.com
Classifier: License :: OSI Approved :: MIT License
Classifier: Operating System :: OS Independent
Classifier: Programming Language :: Python :: 3.7
Classifier: Programming Language :: Python :: 3.8
Classifier: Programming Language :: Python :: 3.9
Classifier: Programming Language :: Python :: 3.10
Requires-Python: >=3.7
License-File: LICENCE.txt
